{
  "chapter_metadata": {
    "chapter_id": "01.Marathi.03",
    "standard": "1",
    "subject": "Lets Play Do Learn",
    "medium": "Marathi",
    "chapter_name": "कौशल्याधिष्ठित उपक्रम"
  },
  "questions": [
    {
      "question_id": 1,
      "question_type": "MCQ",
      "question": "कौशल्याधिष्ठित उपक्रम म्हणजे काय?",
      "options": [
        { "option_id": 1, "text": "फक्त खेळ", "is_correct": false },
        { "option_id": 2, "text": "कौशल्य विकसित करणारे उपक्रम", "is_correct": true },
        { "option_id": 3, "text": "फक्त अभ्यास", "is_correct": false },
        { "option_id": 4, "text": "विश्रांती", "is_correct": false }
      ],
      "answer": "कौशल्य विकसित करणारे उपक्रम"
    },
    {
      "question_id": 2,
      "question_type": "MCQ",
      "question": "चित्रातील ठसे ओळखण्याचा उद्देश काय आहे?",
      "options": [
        { "option_id": 1, "text": "वेळ घालवणे", "is_correct": false },
        { "option_id": 2, "text": "वस्तू ओळखण्याचे कौशल्य वाढवणे", "is_correct": true },
        { "option_id": 3, "text": "खेळ थांबवणे", "is_correct": false },
        { "option_id": 4, "text": "लिहिणे टाळणे", "is_correct": false }
      ],
      "answer": "वस्तू ओळखण्याचे कौशल्य वाढवणे"
    },
    {
      "question_id": 3,
      "question_type": "MCQ",
      "question": "रिकाम्या चौकोनात विद्यार्थी काय देतात?",
      "options": [
        { "option_id": 1, "text": "अक्षरे", "is_correct": false },
        { "option_id": 2, "text": "वस्तू किंवा हातांचे ठसे", "is_correct": true },
        { "option_id": 3, "text": "संख्या", "is_correct": false },
        { "option_id": 4, "text": "शब्द", "is_correct": false }
      ],
      "answer": "वस्तू किंवा हातांचे ठसे"
    },
    {
      "question_id": 4,
      "question_type": "MCQ",
      "question": "नैसर्गिक वस्तूंचे ठसे कशापासून घेतात?",
      "options": [
        { "option_id": 1, "text": "प्लास्टिक", "is_correct": false },
        { "option_id": 2, "text": "फळभाज्यांचे काप व पाने", "is_correct": true },
        { "option_id": 3, "text": "लोखंड", "is_correct": false },
        { "option_id": 4, "text": "काच", "is_correct": false }
      ],
      "answer": "फळभाज्यांचे काप व पाने"
    },
    {
      "question_id": 5,
      "question_type": "MCQ",
      "question": "बोटांचे ठसे कसे घेतात?",
      "options": [
        { "option_id": 1, "text": "पाण्यात बुडवून", "is_correct": false },
        { "option_id": 2, "text": "रंग किंवा शाई लावून", "is_correct": true },
        { "option_id": 3, "text": "खडूने", "is_correct": false },
        { "option_id": 4, "text": "पेन्सिलने", "is_correct": false }
      ],
      "answer": "रंग किंवा शाई लावून"
    },
    {
      "question_id": 6,
      "question_type": "MCQ",
      "question": "ठसे देऊन काय तयार करतात?",
      "options": [
        { "option_id": 1, "text": "निबंध", "is_correct": false },
        { "option_id": 2, "text": "सौंदर्याकृती", "is_correct": true },
        { "option_id": 3, "text": "उदाहरणे", "is_correct": false },
        { "option_id": 4, "text": "प्रश्न", "is_correct": false }
      ],
      "answer": "सौंदर्याकृती"
    },
    {
      "question_id": 7,
      "question_type": "MCQ",
      "question": "कागदी पंखा कशापासून तयार करतात?",
      "options": [
        { "option_id": 1, "text": "कार्डबोर्ड", "is_correct": false },
        { "option_id": 2, "text": "वर्तमानपत्र किंवा मासिकाचा कागद", "is_correct": true },
        { "option_id": 3, "text": "कापड", "is_correct": false },
        { "option_id": 4, "text": "प्लास्टिक", "is_correct": false }
      ],
      "answer": "वर्तमानपत्र किंवा मासिकाचा कागद"
    },
    {
      "question_id": 8,
      "question_type": "MCQ",
      "question": "कागदी पंखा तयार करताना काय करतात?",
      "options": [
        { "option_id": 1, "text": "सरळ कापतात", "is_correct": false },
        { "option_id": 2, "text": "उलटसुलट घड्या घालतात", "is_correct": true },
        { "option_id": 3, "text": "रंग भरतात", "is_correct": false },
        { "option_id": 4, "text": "फाडतात", "is_correct": false }
      ],
      "answer": "उलटसुलट घड्या घालतात"
    },
    {
      "question_id": 9,
      "question_type": "MCQ",
      "question": "कागदी पंख्यासाठी काड्या कशासाठी लावतात?",
      "options": [
        { "option_id": 1, "text": "सजावटीसाठी", "is_correct": false },
        { "option_id": 2, "text": "धरायला सोपे होण्यासाठी", "is_correct": true },
        { "option_id": 3, "text": "खेळण्यासाठी", "is_correct": false },
        { "option_id": 4, "text": "कापण्यासाठी", "is_correct": false }
      ],
      "answer": "धरायला सोपे होण्यासाठी"
    },
    {
      "question_id": 10,
      "question_type": "MCQ",
      "question": "काड्या चिकटवण्यासाठी काय वापरतात?",
      "options": [
        { "option_id": 1, "text": "पाणी", "is_correct": false },
        { "option_id": 2, "text": "डिंक", "is_correct": true },
        { "option_id": 3, "text": "तेल", "is_correct": false },
        { "option_id": 4, "text": "माती", "is_correct": false }
      ],
      "answer": "डिंक"
    },
    {
      "question_id": 11,
      "question_type": "MCQ",
      "question": "चिकटवलेला भाग कधी उघडावा?",
      "options": [
        { "option_id": 1, "text": "लगेच", "is_correct": false },
        { "option_id": 2, "text": "सुकल्यानंतर", "is_correct": true },
        { "option_id": 3, "text": "ओलसर असताना", "is_correct": false },
        { "option_id": 4, "text": "अर्धवट", "is_correct": false }
      ],
      "answer": "सुकल्यानंतर"
    },
    {
      "question_id": 12,
      "question_type": "MCQ",
      "question": "नैसर्गिक वस्तूंच्या ठशांमुळे काय वाढते?",
      "options": [
        { "option_id": 1, "text": "आळस", "is_correct": false },
        { "option_id": 2, "text": "निरीक्षण कौशल्य", "is_correct": true },
        { "option_id": 3, "text": "थकवा", "is_correct": false },
        { "option_id": 4, "text": "भीती", "is_correct": false }
      ],
      "answer": "निरीक्षण कौशल्य"
    },
    {
      "question_id": 13,
      "question_type": "MCQ",
      "question": "कागदी पंखा हा कोणत्या उपक्रमात येतो?",
      "options": [
        { "option_id": 1, "text": "गरजाधिष्ठित", "is_correct": false },
        { "option_id": 2, "text": "कौशल्याधिष्ठित", "is_correct": true },
        { "option_id": 3, "text": "मनोरंजनात्मक", "is_correct": false },
        { "option_id": 4, "text": "बैठा खेळ", "is_correct": false }
      ],
      "answer": "कौशल्याधिष्ठित"
    },
    {
      "question_id": 14,
      "question_type": "MCQ",
      "question": "हे उपक्रम करताना काय आवश्यक आहे?",
      "options": [
        { "option_id": 1, "text": "घाई", "is_correct": false },
        { "option_id": 2, "text": "सावधपणा", "is_correct": true },
        { "option_id": 3, "text": "गोंधळ", "is_correct": false },
        { "option_id": 4, "text": "आळस", "is_correct": false }
      ],
      "answer": "सावधपणा"
    },
    {
      "question_id": 15,
      "question_type": "MCQ",
      "question": "कौशल्याधिष्ठित उपक्रम कोणासाठी आहेत?",
      "options": [
        { "option_id": 1, "text": "फक्त शिक्षकांसाठी", "is_correct": false },
        { "option_id": 2, "text": "विद्यार्थ्यांसाठी", "is_correct": true },
        { "option_id": 3, "text": "फक्त मोठ्यांसाठी", "is_correct": false },
        { "option_id": 4, "text": "पालकांसाठी", "is_correct": false }
      ],
      "answer": "विद्यार्थ्यांसाठी"
    },

    {
      "question_id": 16,
      "question_type": "SHORT",
      "question": "कौशल्याधिष्ठित उपक्रम म्हणजे काय?",
      "answer": "ज्या उपक्रमांमुळे विद्यार्थ्यांची कौशल्ये विकसित होतात ते कौशल्याधिष्ठित उपक्रम होत."
    },
    {
      "question_id": 17,
      "question_type": "SHORT",
      "question": "नैसर्गिक वस्तूंचे ठसे कशासाठी घेतात?",
      "answer": "वस्तू ओळखण्यासाठी आणि सौंदर्याकृती तयार करण्यासाठी घेतात."
    },
    {
      "question_id": 18,
      "question_type": "SHORT",
      "question": "नैसर्गिक ठशांसाठी कोणत्या वस्तू वापरतात?",
      "answer": "फळभाज्यांचे काप, पाने आणि बिया वापरतात."
    },
    {
      "question_id": 19,
      "question_type": "SHORT",
      "question": "बोटांचे ठसे कसे घेतात?",
      "answer": "बोटांना रंग किंवा शाई लावून ठसे घेतात."
    },
    {
      "question_id": 20,
      "question_type": "SHORT",
      "question": "ठसे देऊन काय तयार करतात?",
      "answer": "ठसे देऊन सुंदर चित्र किंवा सौंदर्याकृती तयार करतात."
    },
    {
      "question_id": 21,
      "question_type": "SHORT",
      "question": "कागदी पंखा कशापासून बनवतात?",
      "answer": "वर्तमानपत्र किंवा मासिकाच्या कागदापासून बनवतात."
    },
    {
      "question_id": 22,
      "question_type": "SHORT",
      "question": "कागदी पंख्यासाठी घड्या का घालतात?",
      "answer": "पंखा नीट उघडण्यासाठी घड्या घालतात."
    },
    {
      "question_id": 23,
      "question_type": "SHORT",
      "question": "काड्या कशासाठी लावतात?",
      "answer": "पंखा धरायला सोपा होण्यासाठी काड्या लावतात."
    },
    {
      "question_id": 24,
      "question_type": "SHORT",
      "question": "डिंक कशासाठी वापरतात?",
      "answer": "काड्या आणि कागद चिकटवण्यासाठी डिंक वापरतात."
    },
    {
      "question_id": 25,
      "question_type": "SHORT",
      "question": "चिकटवलेला भाग कधी उघडावा?",
      "answer": "डिंक सुकल्यानंतरच उघडावा."
    },
    {
      "question_id": 26,
      "question_type": "SHORT",
      "question": "या उपक्रमांमुळे कोणते कौशल्य वाढते?",
      "answer": "निरीक्षण आणि हाताची सफाई वाढते."
    },
    {
      "question_id": 27,
      "question_type": "SHORT",
      "question": "कौशल्याधिष्ठित उपक्रम करताना काय काळजी घ्यावी?",
      "answer": "सावधपणे आणि शिक्षकांच्या मार्गदर्शनाखाली करावे."
    },
    {
      "question_id": 28,
      "question_type": "SHORT",
      "question": "कागदी पंखा बनवताना कोणाची मदत घ्यावी?",
      "answer": "शिक्षकांची मदत घ्यावी."
    },
    {
      "question_id": 29,
      "question_type": "SHORT",
      "question": "हे उपक्रम विद्यार्थ्यांना कसे उपयुक्त ठरतात?",
      "answer": "विद्यार्थ्यांची कल्पकता आणि कौशल्ये वाढतात."
    },
    {
      "question_id": 30,
      "question_type": "SHORT",
      "question": "कौशल्याधिष्ठित उपक्रम का महत्त्वाचे आहेत?",
      "answer": "हे उपक्रम विद्यार्थ्यांचा सर्वांगीण विकास करतात."
    }
  ]
}
